dataparcel/VERSION
dataparcel/__init__.py
dataparcel/datapackage.py
dataparcel/utils/__init__.py
dataparcel/utils/metadata_utils.py
dataparcel/utils/validators.py
dataparcel-0.0.1.dist-info/LICENSE.md
dataparcel-0.0.1.dist-info/METADATA
dataparcel-0.0.1.dist-info/WHEEL
dataparcel-0.0.1.dist-info/top_level.txt
dataparcel-0.0.1.dist-info/RECORD
