Metadata-Version: 2.1
Name: dataparcel
Version: 0.0.1
Summary: Serverless ETL framework
Home-page: https://github.com/navikt
Author: NAV IKT
Author-email: paul.bencze@nav.no
License: MIT
Project-URL: Bug Tracker, https://github.com/navikt
Project-URL: Documentation, https://github.com/navikt
Project-URL: Source Code, https://github.com/navikt
Keywords: datapackage serverless etl jupyter open-data
Platform: UNKNOWN
Classifier: Development Status :: 3 - Alpha
Classifier: License :: OSI Approved :: MIT License
Classifier: Programming Language :: Python :: 3.6
Classifier: Programming Language :: Python :: 3.7
Requires-Python: >=3.6
Requires-Dist: pandas (==0.23.3)
